FletBot/__init__.py
FletBot/felt_bot.py
FletBot/Handlers/__init__.py
FletBot/Handlers/base_handler.py
FletBot/Handlers/derived_handlers.py
FletBot/Keyboards/__init__.py
FletBot/Keyboards/keyboard_builder.py
FletBot/Markups/__init__.py
FletBot/Markups/markup_builder.py
flet_bot-0.0.5.dist-info/LICENSE.md
flet_bot-0.0.5.dist-info/METADATA
flet_bot-0.0.5.dist-info/WHEEL
flet_bot-0.0.5.dist-info/top_level.txt
flet_bot-0.0.5.dist-info/RECORD
