Metadata-Version: 2.1
Name: flet_bot
Version: 0.0.5
Summary: Simplify the development of a Telegram bot
Author: Rarenats (Dmitriy Rarenastu)
Author-email: <>
Keywords: python,telegram bot,telegram bots,telegram,bot,bots
Classifier: Development Status :: 1 - Planning
Classifier: Intended Audience :: Developers
Classifier: Programming Language :: Python :: 3
Classifier: Operating System :: Unix
Classifier: Operating System :: MacOS :: MacOS X
Classifier: Operating System :: Microsoft :: Windows
License-File: LICENSE.md
Requires-Dist: pyTelegramBotAPI
Requires-Dist: APScheduler
Requires-Dist: asyncio
Requires-Dist: aiohttp
Requires-Dist: loguru
